Workbook

Sheet Overzicht & Scenario's
A1: 👑 SLOPER KING™ — OVERZICHT & SCENARIO ANALYSE (SINGLE VS. PAIR)
A2: D2C Webshop verkoop | Uitsplitsing per producttype (Single Unit vs. Complete Pair) per scenario
C3: SCENARIO 1 (10 Single / 10 Pair) | E3: SCENARIO 2 (20 Single / 20 Pair) | G3: SCENARIO 3 (30 Single / 30 Pair)
A4: Parameter / Kostenpost | B4: Bron / Eenheid | C4: Single (10x) | D4: Pair (10x) | E4: Single (20x) | F4: Pair (20x) | G4: Single (30x) | H4: Pair (30x)
A5: VERKOOPVOLUMES (PER MAAND)
A6: Verkocht Volume (Orders / mnd) | B6: stuks/mnd | C6: 10 | D6: 10 | E6: 20 | F6: 20 | G6: 30 | H6: 30
A7: UNIT ECONOMICS & PRIJZEN
A8: Verkoopprijs per Unit | B8: EUR / stuk | C8: 24.95 | D8: 44.95 | E8: 24.95 | F8: 44.95 | G8: 24.95 | H8: 44.95
A9: COGS per Unit (Materiaalkost) | B9: EUR / stuk | C9: ='COGS Detail'!E13 | D9: ='COGS Detail'!G13 | E9: ='COGS Detail'!E13 | F9: ='COGS Detail'!G13 | G9: ='COGS Detail'!E13 | H9: ='COGS Detail'!G13
A10: Stripe Transactiekost per Order | B10: EUR / order | C10: =C8*0.015+0.25 | D10: =D8*0.015+0.25 | E10: =E8*0.015+0.25 | F10: =F8*0.015+0.25 | G10: =G8*0.015+0.25 | H10: =H8*0.015+0.25
A11: Gemiddelde Verzendsubsidie per order | B11: EUR / order | C11: ='Verzendkosten'!G15 | D11: ='Verzendkosten'!G15 | E11: ='Verzendkosten'!G15 | F11: ='Verzendkosten'!G15 | G11: ='Verzendkosten'!G15 | H11: ='Verzendkosten'!G15
A12: 1. INKOMSTEN (BRUTO OMZET)
A13: Bruto Omzet per Maand | B13: EUR / mnd | C13: =C6*C8 | D13: =D6*D8 | E13: =E6*E8 | F13: =F6*F8 | G13: =G6*G8 | H13: =H6*H8
A14: Bruto Omzet per Jaar | B14: EUR / jaar | C14: =C13*12 | D14: =D13*12 | E14: =E13*12 | F14: =F13*12 | G14: =G13*12 | H14: =H13*12
A15: 2. KOSTEN OVERZICHT (PER TYPE & VERDEELD)
A16: Productiekosten (COGS) | B16: EUR / mnd | C16: =C6*C9 | D16: =D6*D9 | E16: =E6*E9 | F16: =F6*F9 | G16: =G6*G9 | H16: =H6*H9
A17: Stripe Betalingskosten | B17: EUR / mnd | C17: =C6*C10 | D17: =D6*D10 | E17: =E6*E10 | F17: =F6*F10 | G17: =G6*G10 | H17: =H6*H10
A18: Verzendsubsidie & Logistiek | B18: EUR / mnd | C18: =C6*C11 | D18: =D6*D11 | E18: =E6*E11 | F18: =F6*F11 | G18: =G6*G11 | H18: =H6*H11
A19: Social Media Marketing (Meta Ads split) | B19: EUR / mnd | C19: 50 | D19: 50 | E19: 125 | F19: 125 | G19: 225 | H19: 225
A20: Vaste Kosten & Afschrijving (50/50 split) | B20: EUR / mnd | C20: ='Investeringen'!F14/2 | D20: ='Investeringen'!F14/2 | E20: ='Investeringen'!F14/2 | F20: ='Investeringen'!F14/2 | G20: ='Investeringen'!F14/2 | H20: ='Investeringen'!F14/2
A21: TOTALE KOSTEN PER MAAND | B21: EUR / mnd | C21: =SUM(C16:C20) | D21: =SUM(D16:D20) | E21: =SUM(E16:E20) | F21: =SUM(F16:F20) | G21: =SUM(G16:G20) | H21: =SUM(H16:H20)
A22: TOTALE KOSTEN PER JAAR | B22: EUR / jaar | C22: =C21*12 | D22: =D21*12 | E22: =E21*12 | F22: =F21*12 | G22: =G21*12 | H22: =H21*12
A23: 3. NETTO RESULTAAT PER PRODUCTTYPE
A24: NETTO WINST PER MAAND | B24: EUR / mnd | C24: =C13-C21 | D24: =D13-D21 | E24: =E13-E21 | F24: =F13-F21 | G24: =G13-G21 | H24: =H13-H21
A25: NETTO WINST PER JAAR | B25: EUR / jaar | C25: =C24*12 | D25: =D24*12 | E25: =E24*12 | F25: =F24*12 | G25: =G24*12 | H25: =H24*12
A26: NETTO WINSTMARGE (%) | B26: % | C26: =C24/C13 | D26: =D24/D13 | E26: =E24/E13 | F26: =F24/F13 | G26: =G24/G13 | H26: =H24/H13
A27: 4. GECOMBINEERD SCENARIO TOTAAL (SINGLE + PAIR SAMEN)
A28: Totale Gecombineerde Omzet / Maand | B28: EUR / mnd | C28: =C13+D13 | E28: =E13+F13 | G28: =G13+H13
A29: Totale Gecombineerde Kosten / Maand | B29: EUR / mnd | C29: =C21+D21 | E29: =E21+F21 | G29: =G21+H21
A30: TOTALE NETTO WINST PER MAAND | B30: EUR / mnd | C30: =C24+D24 | E30: =E24+F24 | G30: =G24+H24
A31: TOTALE NETTO WINST PER JAAR | B31: EUR / jaar | C31: =C30*12 | E31: =E30*12 | G31: =G30*12
A32: GEZAMENLIJKE WINSTMARGE (%) | B32: % | C32: =C30/C28 | E32: =E30/E28 | G32: =G30/G28

Sheet COGS Detail
A1: 🔬 COGS DETAIL & STUKSPRIJS BEREKENING
A2: Exacte materiaalkosten per onderdeel en vergelijking Single Unit vs. Complete Pair
A4: Onderdeel / Materiaal | B4: Specificatie & Leverancier | C4: Basiskost per Item | D4: Aantal Single (1x) | E4: Kost Single (1x) | F4: Aantal Pair (2x) | G4: Kost Pair (2x) | H4: Opmerking
A5: PLA Filament | B5: eSUN / Bambu Lab (~76g/unit) | C5: 0.94 | D5: 1 | E5: =C5*D5 | F5: 2 | G5: =C5*F5 | H5: 0.94 per geprinte unit
A6: Sand paper (GoldX) | B6: CROP GoldX 220-grit contactstrip | C6: 0.14 | D6: 1 | E6: =C6*D6 | F6: 2 | G6: =C6*F6 | H6: 0.14 per contactstrip
A7: Rope (Semi-statisch 4mm) | B7: Petzl 800kg load cord | C7: 0.43 | D7: 1 | E7: =C7*D7 | F7: 2 | G7: =C7*F7 | H7: 0.43 per voorgemonteerd koord
A8: Laser print / Sticker | B8: Zwart op wit laser badge | C8: 0.5 | D8: 1 | E8: =C8*D8 | F8: 2 | G8: =C8*F8 | H8: 0.50 per unit branding
A9: Double naamkaartje | B9: Instructie & QR quickstart | C9: 0.25 | D9: 1 | E9: =C9*D9 | F9: 1 | G9: =C9*F9 | H9: Slechts 1x per bestelling/doos
A10: Cotton bag + Stamp | B10: Katoenen draagtasje met BamBum stempel | C10: 0.67 | D10: 0 | E10: =C10*D10 | F10: 1 | G10: =C10*F10 | H10: Enkel inbegrepen bij Pair (1x)
A11: Verzendzakje / Doosje | B11: Brievenbusverpakking | C11: 0.67 | D11: 1 | E11: =C11*D11 | F11: 0 | G11: =C11*F11 | H11: Single verpakking
A13: TOTALE UNIT COST (COGS) | B13: Productiekost per verpakte eenheid | C13: - | D13: 1x Single | E13: =SUM(E5:E11) | F13: 1x Pair | G13: =SUM(G5:G11) | H13: Gevalideerd: Single €2.93 | Pair €4.95

Sheet Uitgaven & Inkoop
A1: 🛒 UITGAVEN & INKOOP LOGBOEK (BATCHES)
A2: Inkoop van grondstoffen, materialen en bulkorders ter herberekening van de eenheidskosten
A4: Datum / Bestelling | B4: Leverancier / Winkel | C4: Gekocht Materiaal | D4: Totaalbedrag Factuur (EUR) | E4: Aantal Eenheden in Batch | F4: Berekende Kost per Stuk (EUR) | G4: Koppeling naar COGS Item
A5: Batch 1 Inkoop | B5: eSUN / 3DPrima | C5: Matzwart PLA Filament (10x 1kg spoelen) | D5: 188 | E5: 200 | F5: =D5/E5 | G5: PLA Filament (€0.94 / unit)
A6: Batch 1 Inkoop | B6: CROP | C6: GoldX 220-Grit Schuurpapier rol (25m) | D6: 35 | E6: 250 | F6: =D6/E6 | G6: Sand paper (€0.14 / strip)
A7: Batch 1 Inkoop | B7: Deporvillage | C7: Petzl 4mm Semi-statisch koord (100m) | D7: 50.59 | E7: 118 | F7: =D7/E7 | G7: Rope (€0.43 / stuk)
A8: Batch 1 Inkoop | B8: Custom Textiel | C8: Katoenen zakjes + BamBum Stempel (100 stuks) | D8: 67 | E8: 100 | F8: =D8/E8 | G8: Cotton bag + Stamp (€0.67)
A9: Batch 1 Inkoop | B9: Laser Service | C9: Matzwarte Laser Stickers (200 stuks) | D9: 100 | E9: 200 | F9: =D9/E9 | G9: Laser print (€0.50 / unit)
A10: Batch 1 Inkoop | B10: Drukkerij | C10: Double-sided Quickstart Kaartjes (400 stuks) | D10: 100 | E10: 400 | F10: =D10/E10 | G10: Double naamkaartje (€0.25)
A11: Batch 1 Inkoop | B11: Temu | C11: Verzendzakjes 20x25cm (50 stuks test) | D11: 33.5 | E11: 50 | F11: =D11/E11 | G11: Verzendzakje (€0.67)
A13: TOTAAL GEÏNVESTEERD IN VOORRAAD | D13: =SUM(D5:D11)

Sheet Investeringen
A1: 🛠️ VASTE INVESTERINGEN & TOOLING (CAPEX)
A2: Overzicht van vaste apparatuur, tooling tests en maandelijkse afschrijving
A4: Investering / Tool | B4: Categorie | C4: Kostprijs (EUR) | D4: Status / Toelichting | E4: Afschrijvingstermijn (Mnd) | F4: Maandelijkse Kost (EUR)
A5: Rollagers voor spool holder | B5: Hardware Mod | C5: 6 | D5: Spool holder upgrade | E5: 12 | F5: =C5/E5
A6: Printer A1 mini | B6: 3D Printer | C6: 0 | D6: Reeds in bezit / €0 initiële investering | E6: 12 | F6: =C6/E6
A7: Temu zakjes test (20x25cm en 50) | B7: Verpakking Test | C7: 27.19 | D7: Testverpakking sample batch | E7: 6 | F7: =C7/E7
A8: Double sided tape test | B8: Materiaal Test | C8: 17.19 | D8: Montagetape schuurpapier hechting | E8: 6 | F8: =C8/E8
A9: Hot cutter | B9: Tooling & Snijapparatuur | C9: 58.99 | D9: Professionele touwsnijder / smeltbrander | E9: 24 | F9: =C9/E9
A10: Test UV laser | B10: Branding & Labeling | C10: 15 | D10: UV-uitharding test tool | E10: 12 | F10: =C10/E10
A11: Domein & Hosting Platform (Vercel/Stripe) | B11: Vaste Maandelijkse Software | C11: 0 | D11: Software / webshop hosting | E11: 1 | F11: 30
A14: TOTAAL EENMALIGE CAPEX & MAANDLAST | B14: Gekoppeld aan Dashboard | C14: =SUM(C5:C10) | D14: - | E14: - | F14: =SUM(F5:F11)

Sheet Verzendkosten
A1: 🌍 VERZENDKOSTEN DETAIL & VERVOERDERS BENCHMARK
A2: Werkelijke logistieke tarieven (Inposteasy PUDO, DPD PUDO, DPD direct) vs. klanttarieven en subsidie
A3: 1. ACTIEF VERZENDPROFIEL & SUBSIDIEBEREKENING (GEKOPPELD AAN DASHBOARD)
A4: Bestemming (Land / Regio) | B4: Gekozen Vervoerder & Service | C4: Reële Kost voor Fré (EUR) | D4: Tarief Aangerekend aan Klant (EUR) | E4: Verschil / Subsidie per Order (EUR) | F4: Geschatte Order Mix (%) | G4: Gewogen Subsidie (EUR)
A5: België (Leuven Afhaling) | B5: Lokaal op afspraak te Leuven | C5: 0 | D5: 0 | E5: =C5-D5 | F5: 0.15 | G5: =E5*F5
A6: België (Inpost PUDO / Lockers) | B6: Inposteasy Afhaalpunt / Locker | C6: 3.8 | D6: 3.8 | E6: =C6-D6 | F6: 0.25 | G6: =E6*F6
A7: België (DPD direct Thuis) | B7: DPD Home Delivery met Tracking | C7: 5.62 | D7: 4.95 | E7: =C7-D7 | F7: 0.1 | G7: =E7*F7
A8: Nederland (DPD PUDO / Lockers) | B8: DPD Parcelshop / Locker (Laagste kost) | C8: 6.61 | D8: 5.5 | E8: =C8-D8 | F8: 0.15 | G8: =E8*F8
A9: Nederland (DPD direct Thuis) | B9: DPD Home Delivery met Tracking | C9: 8.35 | D9: 6.95 | E9: =C9-D9 | F9: 0.05 | G9: =E9*F9
A10: Duitsland (DPD PUDO / Lockers) | B10: DPD Parcelshop / Locker | C10: 8.35 | D10: 6.5 | E10: =C10-D10 | F10: 0.1 | G10: =E10*F10
A11: Frankrijk (Inpost PUDO / Lockers) | B11: Inposteasy / Mondial Relay Locker | C11: 7.42 | D11: 5.95 | E11: =C11-D11 | F11: 0.08 | G11: =E11*F11
A12: Luxemburg (Inpost PUDO) | B12: Inposteasy Afhaalpunt / Locker | C12: 7.42 | D12: 5.95 | E12: =C12-D12 | F12: 0.02 | G12: =E12*F12
A13: Spanje & Portugal (Inpost PUDO) | B13: Inposteasy Locker (ES/POR: €10.14) | C13: 10.14 | D13: 7.95 | E13: =C13-D13 | F13: 0.05 | G13: =E13*F13
A14: Italië & Polen (Inpost PUDO) | B14: Inposteasy Locker (IT: €10.14 / PO: €10.99) | C14: 10.4 | D14: 7.95 | E14: =C14-D14 | F14: 0.05 | G14: =E14*F14
A15: TOTAAL / GEWOGEN GEMIDDELDE | B15: Gekoppeld aan Dashboard (G15) | C15: - | D15: - | E15: - | F15: =SUM(F5:F14) | G15: =SUM(G5:G14)
A17: 2. COMPLETE VERVOERDERS BENCHMARK & TARIEVENMATRIX (INPOSTEASY VS. DPD)
A18: Vervoerder & Verzendmethode | B18: BE | C18: NL | D18: LU | E18: FR | F18: ES | G18: POR | H18: IT | I18: PO | J18: GE (DE)
A19: Inposteasy (PUDO Lockers / Afhaalpunten) | B19: 3.8 | C19: 7.42 | D19: 7.42 | E19: 7.42 | F19: 10.14 | G19: 10.14 | H19: 10.14 | I19: 10.99 | J19: -
A20: DPD (PUDO Lockers / Parcelshops) | B20: 3.87 | C20: 6.61 | D20: - | E20: 10.54 | F20: - | G20: - | H20: - | I20: - | J20: 8.35
A21: DPD direct (Thuislevering aan de deur) | B21: 5.62 | C21: 8.35 | D21: - | E21: 12.32 | F21: - | G21: - | H21: - | I21: - | J21: 10.12

Sheet Vrienden & Afhaling
A1: 🤝 VRIENDENKORTING & AFHAALPRIJZEN (LEUVEN)
A2: Berekening van vriendenprijzen op basis van wegvallende marketing- (CAC), verpakkings- en verzendkosten
A4: Scenario / Verkoopkanaal | B4: Officiële Webshopprijs | C4: Bespaarde Kosten per Order | D4: Aanbevolen Vriendenprijs | E4: Toegepaste Korting (€) | F4: Toegepaste Korting (%) | G4: COGS (Materiaalkost) | H4: Jouw Nettowinst (€) | I4: Nettowinstmarge (%)
A5: SCENARIO A: GEEN MARKETING (CAC = €0), WEL VERZENDING VIA BPOST / POSTNL
A6: Single Unit (1x) — Verzonden via Post | B6: 24.95 | C6: 6.5 | D6: 20 | E6: =B6-D6 | F6: =E6/B6 | G6: ='COGS Detail'!E13 | H6: =D6-G6-(D6*0.015+0.25)-'Verzendkosten'!G15 | I6: =H6/D6
A7: Complete Pair (2x) — Verzonden via Post | B7: 44.95 | C7: 7.5 | D7: 35 | E7: =B7-D7 | F7: =E7/B7 | G7: ='COGS Detail'!G13 | H7: =D7-G7-(D7*0.015+0.25)-'Verzendkosten'!G15 | I7: =H7/D7
A8: SCENARIO B: GEEN MARKETING (CAC = €0) ÉN LOKALE AFHALING TE LEUVEN (GEEN VERZENDING)
A9: Single Unit (1x) — Afhaling te Leuven / Klimzaal | B9: 24.95 | C9: 8.71 | D9: 16 | E9: =B9-D9 | F9: =E9/B9 | G9: ='COGS Detail'!E13-0.67 | H9: =D9-G9 | I9: =H9/D9
A10: Complete Pair (2x) — Afhaling te Leuven / Klimzaal | B10: 44.95 | C10: 10 | D10: 30 | E10: =B10-D10 | F10: =E10/B10 | G10: ='COGS Detail'!G13 | H10: =D10-G10 | I10: =H10/D10
A12: DETAIL OVERZICHT: WAAROM KAN DEZE KORTING GEGEVEN WORDEN?
A13: Kostencomponent per Order | B13: Reguliere Webshopklant | C13: Vriend (Scenario A: Verzonden) | D13: Vriend (Scenario B: Afhaling) | E13: Besparing / Verklaring
A14: Social Media Marketing (Meta Ads CAC) | B14: € 6,50 - € 7,50 | C14: € 0,00 | D14: € 0,00 | E14: 100% bespaard via persoonlijke connectie / mond-tot-mond
A15: Verzendsubsidie (Transport Fré) | B15: € 0,92 | C15: € 0,92 | D15: € 0,00 | E15: Volledig uitgespaard bij afhaling te Leuven / zaal
A16: Verzendzakje / Brievenbusdoosje | B16: € 0,67 | C16: € 0,67 | D16: € 0,00 | E16: Geen postverpakking nodig bij directe overhandiging
A17: Stripe Betaaltransactiekosten | B17: € 0,62 - € 0,92 | C17: € 0,55 - € 0,78 | D17: € 0,00 | E17: Geen transactiekosten bij Payconiq, overschrijving of cash
A18: TOTALE BESPAARDE KOSTEN PER ORDER | B18: € 0,00 | C18: € 6,50 à € 7,50 | D18: € 8,70 à € 10,00 | E18: Vloeit integraal door naar een eerlijke vriendenprijs

Sheet B2B Klimzalen & Retail
A1: 🧗 B2B KLIMZALEN & WHOLESALE RETAIL
A2: Wholesale marges voor klimzalen, toonbank display packs en B2B consignatie vs. directe inkoop
A4: Product / Verkoopmodel | B4: Adviesprijs Klant (incl. BTW) | C4: Adviesprijs (excl. 21% BTW) | D4: Inkoopprijs Zaal (excl. BTW) | E4: Marge Klimzaal (€) | F4: Marge Klimzaal (%) | G4: COGS Fré (€) | H4: Nettowinst Fré per Stuk (€) | I4: Nettomarge Fré (%)
A5: 1. DIRECTE INKOOP DOOR KLIMZAAL (35% MARGE VOOR DE ZAAL — BULK FACTUUR)
A6: Single Unit (1x) — Directe Inkoop | B6: 24.95 | C6: =B6/1.21 | D6: =C6*(1-0.35) | E6: =C6-D6 | F6: =E6/C6 | G6: ='COGS Detail'!E13 | H6: =D6-G6 | I6: =H6/D6
A7: Complete Pair (2x) — Directe Inkoop | B7: 44.95 | C7: =B7/1.21 | D7: =C7*(1-0.35) | E7: =C7-D7 | F7: =E7/C7 | G7: ='COGS Detail'!G13 | H7: =D7-G7 | I7: =H7/D7
A8: 2. CONSIGNATIE / TEST-STAND MODEL (25% MARGE VOOR DE ZAAL — BETALING PER VERKOCHT STUK)
A9: Single Unit (1x) — Consignatie | B9: 24.95 | C9: =B9/1.21 | D9: =C9*(1-0.25) | E9: =C9-D9 | F9: =E9/C9 | G9: ='COGS Detail'!E13 | H9: =D9-G9 | I9: =H9/D9
A10: Complete Pair (2x) — Consignatie | B10: 44.95 | C10: =B10/1.21 | D10: =C10*(1-0.25) | E10: =C10-D10 | F10: =E10/C10 | G10: ='COGS Detail'!G13 | H10: =D10-G10 | I10: =H10/D10
A12: 3. GYM TOONBANK DISPLAY PACKS (STARTER BUNDELS)
A13: Display Pakket | B13: Inhoud & Specificatie | C13: B2B Pakketprijs (excl. BTW) | D13: Winkelwaarde Klanten (incl. BTW) | E13: Marge Klimzaal (€) | F13: Totale COGS Fré (€) | G13: Nettowinst Fré per Pakket (€) | H13: Nettomarge Fré (%)
A14: Starter Gym Display Pack | B14: 4x Pair + 2x Single + 1x Demo Unit + Toonbank Display | C14: 120 | D14: 229.7 | E14: =D14/1.21-C14 | F14: =(4*'COGS Detail'!G13)+(2*'COGS Detail'!E13)+5.00 | G14: =C14-F14 | H14: =G14/C14
A15: Pro Gym Restock Pack (10 Pairs) | B15: 10x Complete Pair (inclusief zakjes en guide cards) | C15: 235 | D15: 449.5 | E15: =D15/1.21-C15 | F15: =10*'COGS Detail'!G13 | G15: =C15-F15 | H15: =G15/C15
A17: 4. KLIMZALEN SCHAAL-SCENARIO'S (EXTRA MAANDELIJKSE WINST BOVENOP WEBSHOP)
A18: Netwerk / Partnerzalen | B18: Gem. Verkoop per Zaal | C18: Totaal Pairs / Maand | D18: B2B Omzet / Maand (excl. BTW) | E18: COGS Productiekost / Maand | F18: EXTRA NETTOWINST / MAAND | G18: EXTRA NETTOWINST / JAAR
A19: Piloot (3 partnerzalen: Leuven, Gent, Antwerpen) | B19: 3 pairs / zaal / mnd | C19: 9 | D19: =C19*D7 | E19: =C19*'COGS Detail'!G13 | F19: =D19-E19 | G19: =F19*12
A20: Vlaams Netwerk (8 partnerzalen) | B20: 3 pairs / zaal / mnd | C20: 24 | D20: =C20*D7 | E20: =C20*'COGS Detail'!G13 | F20: =D20-E20 | G20: =F20*12
A21: Benelux Netwerk (15 partnerzalen) | B21: 4 pairs / zaal / mnd | C21: 60 | D21: =C21*D7 | E21: =C21*'COGS Detail'!G13 | F21: =D21-E21 | G21: =F21*12
